setup.py
confluo/__init__.py
confluo/core.py
confluo/errors.py
confluo/helpers.py
confluo/models.py
confluo.egg-info/PKG-INFO
confluo.egg-info/SOURCES.txt
confluo.egg-info/dependency_links.txt
confluo.egg-info/requires.txt
confluo.egg-info/top_level.txt