Metadata-Version: 1.1
Name: confluo
Version: 0.0.3
Summary: Minimalist scalable microservice framework for distributed systems using AMQP/RabbitMQ
Home-page: https://github.com/timofurrer/confluo
Author: Timo Furrer
Author-email: tuxtimo@gmail.com
License: MIT
Keywords: confluo,service,amqp,rabbitmq,scalable,destributed,microservice,framework,library,package,module
Platform: UNKNOWN
Classifier: Programming Language :: Python
Classifier: Programming Language :: Python :: 3
Classifier: Programming Language :: Python :: 3.5
Classifier: Operating System :: OS Independent
Classifier: Environment :: Console
Classifier: License :: OSI Approved :: MIT License
Classifier: Intended Audience :: End Users/Desktop
Classifier: Topic :: Utilities
